incubator_db/__init__.py
incubator_db/db.py
incubator_db/db_gui.py
incubator_db/run_gui.py
incubator_db/setup_db.py
incubator_db-0.1.2.dist-info/LICENSE
incubator_db-0.1.2.dist-info/METADATA
incubator_db-0.1.2.dist-info/WHEEL
incubator_db-0.1.2.dist-info/RECORD
