Metadata-Version: 2.3
Name: incubator-db
Version: 0.1.2
Summary: Simple db package for a Incubator
Author: Thiago Meyer
Author-email: tiagmey@gmail.com
Requires-Python: >=3.10,<4.0
Classifier: Programming Language :: Python :: 3
Classifier: Programming Language :: Python :: 3.10
Classifier: Programming Language :: Python :: 3.11
Classifier: Programming Language :: Python :: 3.12
Classifier: Programming Language :: Python :: 3.13
